nuna/__init__.py
nuna/nuna.py
nuna/utils.py
Nuna-1.0.4.dist-info/METADATA
Nuna-1.0.4.dist-info/WHEEL
Nuna-1.0.4.dist-info/top_level.txt
Nuna-1.0.4.dist-info/RECORD
